anyapi/__init__.py
anyapi/cookies.py
anyapi/exceptions.py
anyapi2-0.0.6.dist-info/LICENSE
anyapi2-0.0.6.dist-info/METADATA
anyapi2-0.0.6.dist-info/WHEEL
anyapi2-0.0.6.dist-info/top_level.txt
anyapi2-0.0.6.dist-info/RECORD
