Metadata-Version: 2.1
Name: anyapi2
Version: 0.0.6
Summary: Boilerplate code for api integrations
Home-page: https://github.com/c0ntribut0r/anyapi
License: MIT
Keywords: requests api
Classifier: Environment :: Web Environment
Classifier: Intended Audience :: Developers
Classifier: License :: OSI Approved :: MIT License
Classifier: Operating System :: OS Independent
Classifier: Programming Language :: Python
Classifier: Programming Language :: Python :: 3.10
Classifier: Topic :: Internet :: WWW/HTTP
Classifier: Topic :: Internet :: WWW/HTTP :: Dynamic Content
License-File: LICENSE
Requires-Dist: requests <=3.0
Requires-Dist: tenacity <=9.0
